PerfmonLibrary/__init__.py
robotframework_perfmon-0.1.dist-info/LICENSE
robotframework_perfmon-0.1.dist-info/METADATA
robotframework_perfmon-0.1.dist-info/WHEEL
robotframework_perfmon-0.1.dist-info/top_level.txt
robotframework_perfmon-0.1.dist-info/RECORD
